{"sections":{"main":{"type":"main-page","disabled":true,"settings":{}},"press_releases_ycUnfV":{"type":"press-releases","disabled":true,"settings":{}},"circulate02_4BPzQ4":{"type":"circulate02","disabled":true,"settings":{"title":"Explore The Fun Of Building"}},"press_releases_blog_VxWafb":{"type":"press-releases-blog","disabled":true,"settings":{"heading":"","marker_style":"style1","description":"","blog":"news","post_limit":4,"columns_desktop":3,"mobile_swipe":true,"image_ratio":"square","show_date":true,"show_excerpt":true,"show_read_more":false,"show_view_all":true,"marker_color":"#fd6262","disable_top_spacing":false,"disable_bottom_spacing":false}},"event_coupons_8Dt8DY":{"type":"event-coupons","blocks":{"item_bYH7aD":{"type":"item","settings":{"coupons_item":"shopify:\/\/shop_images\/Group_9951.png"}},"item_RBNYhE":{"type":"item","settings":{"coupons_item":"shopify:\/\/shop_images\/Group_9952.png"}},"item_RiteYR":{"type":"item","settings":{"coupons_item":"shopify:\/\/shop_images\/Group_9953.png"}}},"block_order":["item_bYH7aD","item_RBNYhE","item_RiteYR"],"settings":{"title":"Exclusive Black Friday Savings -","title_special":"Limited Time","sub_title":"Real Feedback, Real Playtime Magic","mian_img":"shopify:\/\/shop_images\/img_v3_02gl_11b7eda9-ba67-4125-a525-3b942bab245g.png","main_img_mobile":"shopify:\/\/shop_images\/img_v3_02gl_faa9a7c3-5dea-457a-ab58-87e8a38cfe9g.png","top_button_link":"shopify:\/\/collections\/transformers-toys","top_button_link_text":"","top_button_bg":"#ff5f00","bottom_button_bg":"rgba(0,0,0,0)","middle_title":"Shop More, Save More","middle_sub_title":"Get extra discounts when you shop! You can apply the code for your instant savings.","middle_img":"shopify:\/\/shop_images\/img_v3_02gj_ba0c726d-2927-4a82-acd3-c6b06aebe76g.png","bottom_button_link":"https:\/\/blokees.com\/en-us\/","bottom_button_link_text":"","background_color":"#141414","title_color":"#ffffff","title_color_special":"#ff5f00","top_link_color":"#ffffff","middle_bg_color":"#1861e0","middle_text_color":"#ffffff","bottom_link_bg_color":"#ff5f00","bottom_link_color":"#ffffff"}},"pro_showcase_custom_N78RPf":{"type":"pro-showcase-custom","blocks":{"item_KpJDtx":{"type":"item","settings":{"image":"shopify:\/\/shop_images\/Group_9959.png","slide_link":"shopify:\/\/products\/blokees-figures-transformers-galaxy-version-05-one","buttontext":"Galaxy Version 05"}},"item_kJ9TgM":{"type":"item","settings":{"image":"shopify:\/\/shop_images\/Group_9957.png","slide_link":"shopify:\/\/products\/transformers-galaxy-version-04-fractured-space-time","buttontext":"Galaxy Version 04"}},"item_cxnrAb":{"type":"item","settings":{"image":"shopify:\/\/shop_images\/Group_9956.png","slide_link":"shopify:\/\/products\/transformers-galaxy-version-03-the-autobot-run","buttontext":"Galaxy Version 03"}},"item_6XtQaB":{"type":"item","settings":{"image":"shopify:\/\/shop_images\/Group_9955.png","slide_link":"shopify:\/\/products\/blokees-figures-transformers-galaxy-version-02-sos","buttontext":"Galaxy Version 02"}},"item_ricfCn":{"type":"item","settings":{"image":"shopify:\/\/shop_images\/Group_9954.png","slide_link":"shopify:\/\/products\/blokees-figures-transformers-galaxy-version-01-roll-out","buttontext":"Galaxy Version 01"}},"item_PkFwky":{"type":"item","settings":{"image":"shopify:\/\/shop_images\/Group_9964.png","slide_link":"shopify:\/\/products\/blokees-figures-transformers-shining-version-02-shining-1985","buttontext":"Shining Version 02"}},"item_nKMYHA":{"type":"item","settings":{"image":"shopify:\/\/shop_images\/Group_9963.png","slide_link":"shopify:\/\/products\/transformers-classic-class-one-sentinel-prime","buttontext":"Classic Class 14"}},"item_hw8CnX":{"type":"item","settings":{"image":"shopify:\/\/shop_images\/Group_9962.png","slide_link":"shopify:\/\/products\/transformers-classic-class-one-elita-1","buttontext":"Classic Class 13"}},"item_BCD6E9":{"type":"item","settings":{"image":"shopify:\/\/shop_images\/Group_9961.png","slide_link":"shopify:\/\/products\/transformers-classic-class-one-megatron","buttontext":"Classic Class 12"}},"item_4JXtzg":{"type":"item","settings":{"image":"shopify:\/\/shop_images\/Group_9959.png","slide_link":"shopify:\/\/products\/transformers-classic-class-one-optimus-prime","buttontext":"Classic Class 11"}},"item_qyKH9N":{"type":"item","settings":{"image":"shopify:\/\/shop_images\/Group_9973.png","slide_link":"shopify:\/\/products\/transformers-2007-classic-class-megatron","buttontext":"Classic Class 10"}},"item_HC4AQr":{"type":"item","settings":{"image":"shopify:\/\/shop_images\/Group_9972.png","slide_link":"shopify:\/\/products\/transformers-2007-classic-class-optimus-prime","buttontext":"Classic Class 09"}},"item_gctFDz":{"type":"item","settings":{"image":"shopify:\/\/shop_images\/Group_9966.png","slide_link":"shopify:\/\/products\/transformers-classic-class-bumblebee","buttontext":"Classic Class 02"}},"item_jYt6ct":{"type":"item","settings":{"image":"shopify:\/\/shop_images\/Group_9965.png","slide_link":"shopify:\/\/products\/transformers-classic-class-optimus-prime","buttontext":"Classic Class 01"}},"item_kWLqiC":{"type":"item","settings":{"image":"shopify:\/\/shop_images\/Group_9974.png","slide_link":"shopify:\/\/products\/transformers-2024-yearly-version-the-golden-lagoon","buttontext":"X Yearly Version"}}},"block_order":["item_KpJDtx","item_kJ9TgM","item_cxnrAb","item_6XtQaB","item_ricfCn","item_PkFwky","item_nKMYHA","item_hw8CnX","item_BCD6E9","item_4JXtzg","item_qyKH9N","item_HC4AQr","item_gctFDz","item_jYt6ct","item_kWLqiC"],"custom_css":["@media (max-width: 768px) {#template--18512021487854__pro_showcase_custom_N78RPf-showcase .showcase-left .left-title {font-size: calc(3500vw \/ var(--base-width)); text-align: center; }}"],"settings":{"heading":"Blokees Showcase","subtitle":"From New to Exclusive","subtitle2":"Find Your Next Favorite Build Here!","context":"Browse through our new arrivals for the latest innovations","background_color":"#141414","button_bg_color":"#ffffff","button_hover_font_color":"#141414","font_color":"#ffffff","top_image":"shopify:\/\/shop_images\/image242.png"}},"media_show_LhizJj":{"type":"media-show","blocks":{"youtube_video_dQcytp":{"type":"youtube_video","settings":{"video_title_youtube":"Unboxing & Build: ‪Transformers One Classic Class Sentinel Prime","video_external":"https:\/\/www.youtube.com\/watch?v=nP4cqhJdsIU","video_font_color":"#ffffff"}},"social_pyiDUK":{"type":"social","settings":{"info_photo":"shopify:\/\/shop_images\/image_95b81c0c-0e72-4a5e-8eb1-5d99cf6d5fba.png","info_name":"Emma J.","info_des":"Freelance Writer","info_social":"shopify:\/\/shop_images\/Group_9223.svg","content_title":"Unique Designs for Every Character","content_text":"<p>Each figure has a unique look. Love the creativity in this line!<\/p>","content_img":"shopify:\/\/shop_images\/img_v3_02gj_740a4c2b-ee3b-4825-984f-d6d3bed7659g.jpg","content_time":"October 12, 2024","star":5,"font_color":"#006de5","background_color":"#ffffff","star_color":"#006de5","media_text_color":"#ffffff"}},"youtube_video_b7aee9":{"type":"youtube_video","settings":{"video_title_youtube":"Transformers Speed Build! Transformers ONE Figures Collection!!","video_external":"https:\/\/www.youtube.com\/watch?v=-SmrKMhVErA&t=8s","video_font_color":"#ffffff"}},"social_BnTXBx":{"type":"social","settings":{"info_photo":"shopify:\/\/shop_images\/6_21.png","info_name":"Ryan T.","info_des":"Comic Book Artist","info_social":"shopify:\/\/shop_images\/Symbol_svg.svg","content_title":"Fantastic Details for Every Character","content_text":"<p>As an artist, I appreciate the intricate details on each figure. Truly impressive work!<\/p>","content_img":"shopify:\/\/shop_images\/img_v3_02gj_5df4dc43-1924-4b02-b1c8-75cfee0ede2g.jpg","content_time":"October 8, 2024","star":4,"font_color":"#006de5","background_color":"#ffffff","star_color":"#006de5","media_text_color":"#ffffff"}},"youtube_video_YnwNRh":{"type":"youtube_video","settings":{"video_title_youtube":"Transformers: The Brilliance of BLOKEES!","video_external":"https:\/\/www.youtube.com\/watch?v=WweW64Gm5vE&pp=ygUHYmxva2Vlcw%3D%3D","video_font_color":"#ffffff"}},"social_yytEAB":{"type":"social","settings":{"info_photo":"shopify:\/\/shop_images\/6_15.png","info_name":"Sophia R.","info_des":"Stay-at-Home Mom","info_social":"shopify:\/\/shop_images\/Group_9223.svg","content_title":"A Big Hit with the Kids!","content_text":"<p>My sons adore these figures! Built to last through all their playtime adventures.<\/p>","content_img":"shopify:\/\/shop_images\/img_v3_02gj_202ddfbe-ca24-4670-98bf-2a9d3cad800g.jpg","content_time":"October 1, 2024","star":5,"font_color":"#006de5","background_color":"#ffffff","star_color":"#006de5","media_text_color":"#ffffff"}},"youtube_video_8DEPXp":{"type":"youtube_video","settings":{"video_title_youtube":"Transformers One Build | Megatron | Blokees Classic Class","video_external":"https:\/\/www.youtube.com\/watch?v=Z8TmGPr9ByI&t=12s","video_font_color":"#ffffff"}},"social_t4KyYG":{"type":"social","settings":{"info_photo":"shopify:\/\/shop_images\/6_10.png","info_name":"Lucas M.","info_des":"Graphic Designer","info_social":"shopify:\/\/shop_images\/Symbol_svg.svg","content_title":"Nostalgia with a Modern Twist","content_text":"<p>The Galaxy Version set brings back memories with a sleek, updated look. Love it for display!<\/p>","content_img":"shopify:\/\/shop_images\/img_v3_02gj_41255013-a8ac-478b-8747-6ce320ee15ag.jpg","content_time":"September 22, 2024","star":4,"font_color":"#006de5","background_color":"#ffffff","star_color":"#006de5","media_text_color":"#ffffff"}},"youtube_video_yac4Je":{"type":"youtube_video","settings":{"video_title_youtube":"Blokees Transformers Classic Class (Rise of the Beasts)","video_external":"https:\/\/www.youtube.com\/watch?v=xKgrJx-Sf3Q","video_font_color":"#ffffff"}},"social_yfRCT9":{"type":"social","settings":{"info_photo":"shopify:\/\/shop_images\/6_22.png","info_name":"Olivia P.","info_des":"Elementary School Teacher","info_social":"shopify:\/\/shop_images\/Group_9223.svg","content_title":"Creative Play for Kids","content_text":"<p>A classroom favorite! These durable figures keep my students engaged and entertained.<\/p>","content_img":"shopify:\/\/shop_images\/img_v3_02gj_c5cff0f6-a027-4ea5-9cbe-3b787f79a08g.jpg","content_time":"September 1, 2024","star":5,"font_color":"#006de5","background_color":"#ffffff","star_color":"#006de5","media_text_color":"#ffffff"}},"youtube_video_D6eWxb":{"type":"youtube_video","settings":{"video_title_youtube":"Action Figures Bloks Transformers One CC14 Sentinel Prime","video_external":"https:\/\/www.youtube.com\/watch?v=rMJPBKs8_OQ&pp=ygUHYmxva2Vlcw%3D%3D","video_font_color":"#ffffff"}},"social_YR3Xje":{"type":"social","settings":{"info_photo":"shopify:\/\/shop_images\/6_11.png","info_name":"Tom W.","info_des":"Toy Collector","info_social":"shopify:\/\/shop_images\/Group_9223.svg","content_title":"Top-Notch Quality and Details","content_text":"<p>The Galaxy Version set is a standout in my collection. Great for display or action poses!<\/p>","content_img":"shopify:\/\/shop_images\/img_v3_02gj_5f6080ab-ea4b-4e4c-b411-72b02595137g_758b1ba7-8bd6-483b-887d-ab4d75a056f5.jpg","content_time":"August 15, 2024","star":5,"font_color":"#006de5","background_color":"#ffffff","star_color":"#006de5","media_text_color":"#ffffff"}},"youtube_video_VnW3Bb":{"type":"youtube_video","settings":{"video_title_youtube":"BLOKEES Transformers Action\/Legendary Edition Voyager Scaled OPTIMUS PRIME Review","video_external":"https:\/\/www.youtube.com\/watch?v=TLeE8l1IZ4M","video_font_color":"#ffffff"}},"youtube_video_WhMwz7":{"type":"youtube_video","settings":{"video_title_youtube":"Blokees Transformers One Galaxy Version 05 ONE Speed Build","video_external":"https:\/\/www.youtube.com\/watch?v=2DuC5vfrdHY","video_font_color":"#ffffff"}}},"block_order":["youtube_video_dQcytp","social_pyiDUK","youtube_video_b7aee9","social_BnTXBx","youtube_video_YnwNRh","social_yytEAB","youtube_video_8DEPXp","social_t4KyYG","youtube_video_yac4Je","social_yfRCT9","youtube_video_D6eWxb","social_YR3Xje","youtube_video_VnW3Bb","youtube_video_WhMwz7"],"settings":{"title":"what our little builders say","sub_title":"Real Feedback, Real Playtime Magic","background_color":"#141414","text_color":"#ffffff","viwemore_color":"#006de5","viwemore_bg_color":"#ffffff","play_icon":"shopify:\/\/shop_images\/Group_8482.svg"}}},"order":["main","press_releases_ycUnfV","circulate02_4BPzQ4","press_releases_blog_VxWafb","event_coupons_8Dt8DY","pro_showcase_custom_N78RPf","media_show_LhizJj"]}